netbox_interface_synchronization/__init__.py
netbox_interface_synchronization/forms.py
netbox_interface_synchronization/template_content.py
netbox_interface_synchronization/urls.py
netbox_interface_synchronization/utils.py
netbox_interface_synchronization/views.py
netbox_interface_synchronization/templates/netbox_interface_synchronization/compare_interfaces_button.html
netbox_interface_synchronization/templates/netbox_interface_synchronization/interface_comparison.html
netbox_interface_synchronization/templates/netbox_interface_synchronization/number_of_interfaces_panel.html
netbox_interface_synchronization-4.1.7.dist-info/licenses/LICENSE
netbox_interface_synchronization-4.1.7.dist-info/METADATA
netbox_interface_synchronization-4.1.7.dist-info/WHEEL
netbox_interface_synchronization-4.1.7.dist-info/top_level.txt
netbox_interface_synchronization-4.1.7.dist-info/RECORD
