Metadata-Version: 2.4
Name: netbox-interface-synchronization
Version: 4.1.7
Summary: Syncing existing interfaces with the interfaces from a device type template in NetBox 4+
Author: Keith Knowles
Author-email: mkknowles@outlook.com
License: GPL-3.0
License-File: LICENSE
Dynamic: author
Dynamic: author-email
Dynamic: description
Dynamic: description-content-type
Dynamic: license
Dynamic: license-file
Dynamic: summary
